[
  {
    "id": 1,
    "firstname": "Anita",
    "lastname" : "Patil",
    "email" : "anitapatil101@gmail.com",
    "usename": "anitapatil",
    "password": "Anita@123"
    
  },
  {
     "id": 2,
    "firstname": "Rohini",
    "lastname" : "Killedar",
    "email" : "rohini.killedar@gmail.com",
    "usename": "rohinikilledar",
    "password": "Rohini@123"
  },
  {
    "id": 3,
    "firstname": "Komal",
    "lastname" : "Dhere",
    "email" : "komal.dhere1@gmail.com",
    "usename": "komaldhere",
    "password": "komal@123"
  }
]
